cfgc/__init__.py
cfgc/center.py
cfgc/envs/__init__.py
config_center-0.0.40.post2.dist-info/METADATA
config_center-0.0.40.post2.dist-info/WHEEL
config_center-0.0.40.post2.dist-info/licenses/LICENSE.txt
config_center-0.0.40.post2.dist-info/RECORD
