Metadata-Version: 2.3
Name: config-center
Version: 0.0.40.post2
Summary: A site-package to create your local pypi-sitepackage, manage your own scripts pack as an env!
Project-URL: Repository, https://github.com/WhatMelonGua/config-center
Author-email: VaterFus <1107818699@qq.com>
License: MIT License
License-File: LICENSE.txt
Keywords: config,local,pipeline,tool
Requires-Python: >=3.4
Requires-Dist: importlib
Requires-Dist: pathlib
